seven_cloudapp_frame/__init__.py
seven_cloudapp_frame/route.py
seven_cloudapp_frame/handlers/__init__.py
seven_cloudapp_frame/handlers/core.py
seven_cloudapp_frame/handlers/filter_base.py
seven_cloudapp_frame/handlers/frame_base.py
seven_cloudapp_frame/handlers/client/__init__.py
seven_cloudapp_frame/handlers/client/act.py
seven_cloudapp_frame/handlers/client/address.py
seven_cloudapp_frame/handlers/client/app.py
seven_cloudapp_frame/handlers/client/goods.py
seven_cloudapp_frame/handlers/client/ip_c.py
seven_cloudapp_frame/handlers/client/order.py
seven_cloudapp_frame/handlers/client/pay.py
seven_cloudapp_frame/handlers/client/stat.py
seven_cloudapp_frame/handlers/client/task.py
seven_cloudapp_frame/handlers/client/theme.py
seven_cloudapp_frame/handlers/client/user.py
seven_cloudapp_frame/handlers/server/__init__.py
seven_cloudapp_frame/handlers/server/act_s.py
seven_cloudapp_frame/handlers/server/app_s.py
seven_cloudapp_frame/handlers/server/base_s.py
seven_cloudapp_frame/handlers/server/cms_s.py
seven_cloudapp_frame/handlers/server/goods_s.py
seven_cloudapp_frame/handlers/server/ip_s.py
seven_cloudapp_frame/handlers/server/launch_s.py
seven_cloudapp_frame/handlers/server/module_s.py
seven_cloudapp_frame/handlers/server/order_s.py
seven_cloudapp_frame/handlers/server/price_s.py
seven_cloudapp_frame/handlers/server/prize_s.py
seven_cloudapp_frame/handlers/server/report_s.py
seven_cloudapp_frame/handlers/server/task_s.py
seven_cloudapp_frame/handlers/server/theme_s.py
seven_cloudapp_frame/handlers/server/user_s.py
seven_cloudapp_frame/libs/__init__.py
seven_cloudapp_frame/libs/common/__init__.py
seven_cloudapp_frame/libs/common/frame_console.py
seven_cloudapp_frame/libs/common/frame_db.py
seven_cloudapp_frame/libs/common/frame_helper.py
seven_cloudapp_frame/libs/common/frame_tornado.py
seven_cloudapp_frame/libs/common/share_config.py
seven_cloudapp_frame/libs/customize/__init__.py
seven_cloudapp_frame/libs/customize/action_helper.py
seven_cloudapp_frame-1.2.110.dist-info/LICENSE
seven_cloudapp_frame-1.2.110.dist-info/METADATA
seven_cloudapp_frame-1.2.110.dist-info/WHEEL
seven_cloudapp_frame-1.2.110.dist-info/top_level.txt
seven_cloudapp_frame-1.2.110.dist-info/RECORD
