Metadata-Version: 2.1
Name: seven-cloudapp-frame
Version: 1.2.110
Summary: seven cloudapp frame
Home-page: http://gitlab.tdtech.gao7.com/TaoBaoCloud/seven_cloudapp_frame.git
Author: seven
Author-email: tech@gao7.com
License: MIT
Platform: UNKNOWN
Classifier: Topic :: Software Development :: Libraries :: Python Modules
Classifier: Programming Language :: Python
Classifier: Programming Language :: Python :: 3.4
Classifier: Programming Language :: Python :: 3.5
Classifier: Programming Language :: Python :: 3.5
Classifier: Programming Language :: Python :: 3.6
Classifier: Programming Language :: Python :: 3.7
Classifier: Programming Language :: Python :: 3.8
Classifier: Programming Language :: Python :: 3.9
Requires-Python: ~=3.4
Requires-Dist: seven-framework (>=1.2.3)
Requires-Dist: seven-top (>=1.0.28)
Requires-Dist: asq (==1.3)
Requires-Dist: emoji (==1.6.1)
Requires-Dist: xmltodict (==0.12.0)
Requires-Dist: requests (==2.32.3)
Requires-Dist: requests-pkcs12 (==1.25)
Requires-Dist: mmh3 (==3.0.0)
Requires-Dist: bce-python-sdk (==0.8.61)
